[{"__type__":"cc.Prefab","_name":"nodeConsole","data":{"__id__":1}},{"__type__":"cc.Node","_name":"nodeConsole","_children":[{"__id__":2}],"_components":[{"__type__":"cc.Widget","node":{"__id__":1},"_alignFlags":45},{"__type__":"f9cd53c2dlHbpWcSu9oRLfW","node":{"__id__":1}}],"_prefab":{"__type__":"cc.PrefabInfo","root":{"__id__":1},"asset":{"__uuid__":"249ilxnjtJ7YCAF66Ldmgu"},"fileId":"aa1STm89ZOfK4D7Q1p1aKR"},"_contentSize":{"__type__":"cc.Size","width":640,"height":1136},"_trs":{"__type__":"TypedArray","ctor":"Float64Array","array":[320,568,0,0,0,0,1,1,1,1]}},{"__type__":"cc.Node","_name":"nodeLog","_parent":{"__id__":1},"_children":[{"__id__":3},{"__id__":4}],"_components":[{"__type__":"cc.Widget","node":{"__id__":2},"_alignFlags":12,"_originalWidth":800}],"_prefab":{"__type__":"cc.PrefabInfo","root":{"__id__":1},"asset":{"__uuid__":"249ilxnjtJ7YCAF66Ldmgu"},"fileId":"e7vZ+y7nJHE75jmNBtp9Bt"},"_contentSize":{"__type__":"cc.Size","width":800,"height":400},"_trs":{"__type__":"TypedArray","ctor":"Float64Array","array":[80,-368,0,0,0,0,1,1,1,1]}},{"__type__":"cc.Node","_name":"New Sprite(Splash)","_parent":{"__id__":2},"_components":[{"__type__":"cc.Sprite","node":{"__id__":3},"_materials":[{"__uuid__":"ecpdLyjvZBwrvm+cedCcQy"}],"_spriteFrame":{"__uuid__":"a2MjXRFdtLlYQ5ouAFv/+R"},"_sizeMode":0},{"__type__":"cc.Widget","node":{"__id__":3},"_alignFlags":45,"_originalWidth":100,"_originalHeight":100}],"_prefab":{"__type__":"cc.PrefabInfo","root":{"__id__":1},"asset":{"__uuid__":"249ilxnjtJ7YCAF66Ldmgu"},"fileId":"bbCKL7u3pJob0gtQ9BtHfZ"},"_opacity":150,"_color":{"__type__":"cc.Color"},"_contentSize":{"__type__":"cc.Size","width":800,"height":400},"_trs":{"__type__":"TypedArray","ctor":"Float64Array","array":[0,0,0,0,0,0,1,1,1,1]}},{"__type__":"cc.Node","_name":"labelmsg","_parent":{"__id__":2},"_components":[{"__type__":"cc.Label","node":{"__id__":4},"_materials":[{"__uuid__":"ecpdLyjvZBwrvm+cedCcQy"}],"_useOriginalSize":false,"_fontSize":25,"_lineHeight":27,"_N$verticalAlign":2,"_N$overflow":3},{"__type__":"cc.Widget","node":{"__id__":4},"_alignFlags":12,"_left":10,"_bottom":10}],"_prefab":{"__type__":"cc.PrefabInfo","root":{"__id__":1},"asset":{"__uuid__":"249ilxnjtJ7YCAF66Ldmgu"},"fileId":"b5iI1yYxRI+4eY2WLN+zRy"},"_contentSize":{"__type__":"cc.Size","width":780,"height":34.02},"_anchorPoint":{"__type__":"cc.Vec2"},"_trs":{"__type__":"TypedArray","ctor":"Float64Array","array":[-390,-190,0,0,0,0,1,1,1,1]}}]